Metadata-Version: 2.1
Name: mmyolo-open
Version: 0.6.1
Summary: OpenMMLab Toolbox of YOLO
Home-page: https://github.com/open-mmlab/mmyolo
Author: MMYOLO Contributors
Author-email: openmmlab@gmail.com
License: GPL License 3.0
Keywords: computer vision,object detection
Platform: UNKNOWN
Classifier: Development Status :: 5 - Production/Stable
Classifier: License :: OSI Approved :: Apache Software License
Classifier: Operating System :: OS Independent
Classifier: Programming Language :: Python :: 3
Classifier: Programming Language :: Python :: 3.7
Classifier: Programming Language :: Python :: 3.8
Classifier: Programming Language :: Python :: 3.9
License-File: LICENSE
Requires-Dist: numpy
Requires-Dist: prettytable
Provides-Extra: all
Requires-Dist: cython ; extra == 'all'
Requires-Dist: numpy ; extra == 'all'
Requires-Dist: prettytable ; extra == 'all'
Requires-Dist: flake8 ; extra == 'all'
Requires-Dist: interrogate ; extra == 'all'
Requires-Dist: isort ==4.3.21 ; extra == 'all'
Requires-Dist: kwarray ; extra == 'all'
Requires-Dist: memory-profiler ; extra == 'all'
Requires-Dist: mmcls >=1.0.0rc4 ; extra == 'all'
Requires-Dist: mmpose >=1.0.0 ; extra == 'all'
Requires-Dist: mmrazor >=1.0.0rc2 ; extra == 'all'
Requires-Dist: mmrotate >=1.0.0rc1 ; extra == 'all'
Requires-Dist: parameterized ; extra == 'all'
Requires-Dist: protobuf <=3.20.1 ; extra == 'all'
Requires-Dist: psutil ; extra == 'all'
Requires-Dist: pytest ; extra == 'all'
Requires-Dist: ubelt ; extra == 'all'
Requires-Dist: xdoctest >=0.10.0 ; extra == 'all'
Requires-Dist: yapf ; extra == 'all'
Provides-Extra: build
Requires-Dist: cython ; extra == 'build'
Requires-Dist: numpy ; extra == 'build'
Provides-Extra: mim
Requires-Dist: mmcv <=2.1.0,>=2.0.0rc4 ; extra == 'mim'
Requires-Dist: mmdet >=3.0.0 ; extra == 'mim'
Requires-Dist: mmengine >=0.7.1 ; extra == 'mim'
Provides-Extra: tests
Requires-Dist: flake8 ; extra == 'tests'
Requires-Dist: interrogate ; extra == 'tests'
Requires-Dist: isort ==4.3.21 ; extra == 'tests'
Requires-Dist: kwarray ; extra == 'tests'
Requires-Dist: memory-profiler ; extra == 'tests'
Requires-Dist: mmcls >=1.0.0rc4 ; extra == 'tests'
Requires-Dist: mmpose >=1.0.0 ; extra == 'tests'
Requires-Dist: mmrazor >=1.0.0rc2 ; extra == 'tests'
Requires-Dist: mmrotate >=1.0.0rc1 ; extra == 'tests'
Requires-Dist: parameterized ; extra == 'tests'
Requires-Dist: protobuf <=3.20.1 ; extra == 'tests'
Requires-Dist: psutil ; extra == 'tests'
Requires-Dist: pytest ; extra == 'tests'
Requires-Dist: ubelt ; extra == 'tests'
Requires-Dist: xdoctest >=0.10.0 ; extra == 'tests'
Requires-Dist: yapf ; extra == 'tests'
